Metadata-Version: 2.4
Name: facu-weather-flow
Version: 0.1.9
Summary: ETL para extraer, transformar y cargar datos del clima en S3
Home-page: https://github.com/facuvegaingenieer/weather-flow.git
Author: Walter Facundo Vega
Author-email: facundo.vega1234@gmail.com
Requires-Python: >=3.8
License-File: LICENCE
Requires-Dist: pandas
Requires-Dist: boto3
Requires-Dist: pyarrow
Requires-Dist: python-dotenv
Requires-Dist: requests
Dynamic: author
Dynamic: author-email
Dynamic: description
Dynamic: description-content-type
Dynamic: home-page
Dynamic: license-file
Dynamic: requires-dist
Dynamic: requires-python
Dynamic: summary
